utmail/__init__.py
utmail/utmail.py
utmail/api/__init__.py
utmail/api/chacuo.py
utmail-0.1.8.dist-info/LICENSE
utmail-0.1.8.dist-info/METADATA
utmail-0.1.8.dist-info/WHEEL
utmail-0.1.8.dist-info/top_level.txt
utmail-0.1.8.dist-info/RECORD
