Metadata-Version: 2.1
Name: utmail
Version: 0.1.8
Summary: Offer a uniform interface for free temp mail.
Home-page: https://github.com/SpeechlessMatt/UtMail
Author: Czy_4201b
Author-email: speechlessmatt@qq.com
License: MIT
Classifier: Programming Language :: Python :: 3
Classifier: License :: OSI Approved :: MIT License
Classifier: Operating System :: OS Independent
License-File: LICENSE
Requires-Dist: loguru>=0.7.2
Requires-Dist: requests>=2.32.3
